ttpbuilder/HighlighterTEWidget.py
ttpbuilder/__init__.py
ttpbuilder/ttpgui.py
ttpbuilder/Library/__init__.py
ttpbuilder/Library/util.py
ttpbuilder-0.2.dist-info/METADATA
ttpbuilder-0.2.dist-info/WHEEL
ttpbuilder-0.2.dist-info/entry_points.txt
ttpbuilder-0.2.dist-info/top_level.txt
ttpbuilder-0.2.dist-info/RECORD
