Metadata-Version: 2.1
Name: ttpbuilder
Version: 0.2
Summary: A GUI Front end for creating TTP Templates
Home-page: https://github.com/scottpeterman/ttpbuilder
Author: Scott Peterman
Author-email: scottpeterman@gmail.com
License: GPLv3
Classifier: Programming Language :: Python :: 3.9
Classifier: License :: OSI Approved :: GNU General Public License v3 (GPLv3)
Classifier: Operating System :: OS Independent
Requires-Python: >=3.9
Requires-Dist: PyQt6 (==6.5.1)
Requires-Dist: PyQt6-WebEngine (==6.5.0)
Requires-Dist: ttp (==0.9.5)
